{"name":"roc","abilityScores":[{"abilityType":"str","score":28},{"abilityType":"dex","score":10},{"abilityType":"con","score":20},{"abilityType":"int","score":3},{"abilityType":"wis","score":10},{"abilityType":"cha","score":9}],"stats":[{"statType":"ac","statValue":"15"},{"statType":"hp","statValue":"16d20-80"},{"statType":"speed","statValue":"20"},{"statType":"pp","statValue":"10"}],"features":[{"name":"Saves","description":"wis 4, con 9, dex 4, cha 3"},{"name":"Skills","description":"perception 4"},{"name":"Keen Sight","description":"The roc has advantage on Wisdom (Perception) checks that rely on sight."},{"name":"Languages","description":""},{"name":"Challenge","description":"11"}],"actions":[{"name":"\rMultiattack","toHit":"","reach":"","hit":"","description":"The roc makes two attacks: one with its beak and one with its talons."},{"name":"\rBeak","toHit":"","reach":"","hit":"","description":"Melee Weapon Attack: +13 to hit, reach 10 ft., one target. Hit: 27 (4d8 + 9) piercing damage."},{"name":"\rTalons","toHit":"","reach":"","hit":"","description":"Melee Weapon Attack: +13 to hit, reach 5 ft., one target. Hit: 23 (4d6 + 9) slashing damage, and the target is grappled (escape DC 19). Until this grapple ends, the target is restrained, and the roc can\u0027t use its talons on another target."}]}