{"name":"Young Red Dragon","abilityScores":[{"abilityType":"str","score":23},{"abilityType":"dex","score":10},{"abilityType":"con","score":21},{"abilityType":"int","score":14},{"abilityType":"wis","score":11},{"abilityType":"cha","score":19}],"stats":[{"statType":"ac","statValue":"18"},{"statType":"hp","statValue":"17d10+85"},{"statType":"speed","statValue":"40 ft.,climb 40 ft.,fly 80 ft."}],"features":[{"name":"Saves","description":"Dex 4, Con 9, Wis 4, Cha 8"},{"name":"Skills","description":"Perception 8, Stealth 4"},{"name":"DamageImmunities","description":"fire"},{"name":"Senses","description":"blindsight 30 ft., darkvision 120 ft."},{"name":"Languages","description":"Common, Draconic"},{"name":"Challenge Rating","description":"10"}],"actions":[{"name":"Multiattack","toHit":"","reach":"","hit":"","description":"The dragon makes three attacks: one with its bite and two with its claws."},{"name":"Bite","toHit":"","reach":"","hit":"","description":"Melee Weapon Attack: +10 to hit, reach 10 ft., one target. Hit: 17 (2d10 + 6) piercing damage plus 3 (1d6) fire damage."},{"name":"Claw","toHit":"","reach":"","hit":"","description":"Melee Weapon Attack: +10 to hit, reach 5 ft., one target. Hit: 13 (2d6 + 6) slashing damage."},{"name":"Fire Breath (Recharge 5-6)","toHit":"","reach":"","hit":"","description":"The dragon exhales fire in a 30-foot cone. Each creature in that area must make a DC 17 Dexterity saving throw, taking 56 (16d6) fire damage on a failed save, or half as much damage on a successful one."}]}