{"name":"Young Blue Dragon","abilityScores":[{"abilityType":"str","score":21},{"abilityType":"dex","score":10},{"abilityType":"con","score":19},{"abilityType":"int","score":14},{"abilityType":"wis","score":13},{"abilityType":"cha","score":17}],"stats":[{"statType":"ac","statValue":"18"},{"statType":"hp","statValue":"16d10+64"},{"statType":"speed","statValue":"40 ft.,burrow 40 ft.,fly 80 ft."}],"features":[{"name":"Saves","description":"Dex 4, Con 8, Wis 5, Cha 7"},{"name":"Skills","description":"Perception 9, Stealth 4"},{"name":"DamageImmunities","description":"lightning"},{"name":"Senses","description":"blindsight 30 ft., darkvision 120 ft."},{"name":"Languages","description":"Common, Draconic"},{"name":"Challenge Rating","description":"9"}],"actions":[{"name":"Multiattack","toHit":"","reach":"","hit":"","description":"The dragon makes three attacks: one with its bite and two with its claws."},{"name":"Bite","toHit":"","reach":"","hit":"","description":"Melee Weapon Attack: +9 to hit, reach 10 ft., one target. Hit: 16 (2d10 + 5) piercing damage plus 5 (1d10) lightning damage."},{"name":"Claw","toHit":"","reach":"","hit":"","description":"Melee Weapon Attack: +9 to hit, reach 5 ft., one target. Hit: 12 (2d6 + 5) slashing damage."},{"name":"Lightning Breath (Recharge 5-6)","toHit":"","reach":"","hit":"","description":"The dragon exhales lightning in an 60-foot line that is 5 feet wide. Each creature in that line must make a DC 16 Dexterity saving throw, taking 55 (10d10) lightning damage on a failed save, or half as much damage on a successful one."}]}